marslab/__init__.py
marslab/geom.py
marslab/parse.py
marslab/poolutils.py
marslab/slowtime.py
marslab/spectops.py
marslab/time.py
marslab/bandset/__init__.py
marslab/bandset/bandset.py
marslab/bandset/clementine.py
marslab/bandset/m3.py
marslab/bandset/mastcam.py
marslab/bandset/mastcamz.py
marslab/compat/__init__.py
marslab/compat/clementine.py
marslab/compat/m3.py
marslab/compat/mertools.py
marslab/compat/sel_to_roi.py
marslab/compat/xcam.py
marslab/demos/__init__.py
marslab/demos/config.py
marslab/imgops/__init__.py
marslab/imgops/debayer.py
marslab/imgops/imgstats.py
marslab/imgops/imgutils.py
marslab/imgops/loaders.py
marslab/imgops/look.py
marslab/imgops/masking.py
marslab/imgops/pltutils.py
marslab/imgops/regions.py
marslab/imgops/render.py
marslab/tests/__init__.py
marslab/tests/test_bandset.py
marslab/tests/test_debayer.py
marslab/tests/test_debayer_fuzzer.py
marslab/tests/test_geom.py
marslab/tests/test_imgutils.py
marslab/tests/test_look.py
marslab/tests/test_pltutils.py
marslab/tests/test_regions.py
marslab/tests/test_render.py
marslab/tests/test_render_fuzzer.py
marslab/tests/test_slowtime.py
marslab/tests/test_spectops.py
marslab/tests/test_time.py
marslab/tests/test_xcam.py
marslab/tests/data/__init__.py
marslab/tests/data/test_cases.py
marslab/tests/utilz/__init__.py
marslab/tests/utilz/bandset_utilz.py
marslab/tests/utilz/div0.py
marslab/tests/utilz/utilz.py
marslab-0.9.25.dist-info/licenses/LICENSE
marslab-0.9.25.dist-info/METADATA
marslab-0.9.25.dist-info/WHEEL
marslab-0.9.25.dist-info/top_level.txt
marslab-0.9.25.dist-info/RECORD
