Metadata-Version: 2.4
Name: marslab
Version: 0.9.25
Summary: Utilities for working with remote sensing observational data of planetary bodies.
Author-email: "Michael St. Clair" <mstclair@millionconcepts.com>, Chase Million <chase@millionconcepts.com>, Sierra Brown <sierra@millionconcepts.com>
Project-URL: Repository, https://github.com/MillionConcepts/marslab
Classifier: Development Status :: 4 - Beta
Classifier: License :: OSI Approved :: BSD License
Classifier: Operating System :: OS Independent
Classifier: Programming Language :: Python :: 3
Requires-Python: >=3.9
License-File: LICENSE
Requires-Dist: cytoolz
Requires-Dist: dustgoggles
Requires-Dist: more-itertools
Requires-Dist: numpy
Requires-Dist: pandas
Requires-Dist: pathos
Requires-Dist: scipy
Provides-Extra: pdr-load
Requires-Dist: pdr; extra == "pdr-load"
Provides-Extra: tests
Requires-Dist: pytest; extra == "tests"
Requires-Dist: hypothesis; extra == "tests"
Provides-Extra: render
Requires-Dist: pillow; extra == "render"
Requires-Dist: matplotlib; extra == "render"
Provides-Extra: notebooks
Requires-Dist: jupyter; extra == "notebooks"
Provides-Extra: regions
Requires-Dist: astropy; extra == "regions"
Provides-Extra: time
Requires-Dist: sympy; extra == "time"
Requires-Dist: python-dateutil; extra == "time"
Provides-Extra: geom
Requires-Dist: pdr; extra == "geom"
Provides-Extra: strict-reshape
Requires-Dist: sympy; extra == "strict-reshape"
Provides-Extra: histograms
Requires-Dist: fast-histogram; extra == "histograms"
Provides-Extra: masking
Requires-Dist: scikit-image; extra == "masking"
Requires-Dist: opencv; extra == "masking"
Dynamic: license-file
